names_dataset/__init__.py
names_dataset/nd_v1.py
names_dataset/nd_v2.py
names_dataset/v1/first_names.all.txt
names_dataset/v1/last_names.all.txt
names_dataset/v2/first_names.zip
names_dataset/v2/last_names.zip
names_dataset-2.0.1.data/data/names_dataset/first_names.all.txt
names_dataset-2.0.1.data/data/names_dataset/first_names.zip
names_dataset-2.0.1.data/data/names_dataset/last_names.all.txt
names_dataset-2.0.1.data/data/names_dataset/last_names.zip
names_dataset-2.0.1.dist-info/LICENSE
names_dataset-2.0.1.dist-info/METADATA
names_dataset-2.0.1.dist-info/WHEEL
names_dataset-2.0.1.dist-info/top_level.txt
names_dataset-2.0.1.dist-info/RECORD
