Metadata-Version: 2.1
Name: names-dataset
Version: 2.0.1
Summary: Probably the biggest dataset of Names, worldwide
Home-page: UNKNOWN
Author: Philippe Remy
Author-email: UNKNOWN
License: MIT
Platform: UNKNOWN
